{"metadata": {"dbt_schema_version": "https://schemas.getdbt.com/dbt/run-results/v4.json", "dbt_version": "1.5.2", "generated_at": "2023-07-07T13:05:47.903477Z", "invocation_id": "0764c9ec-40e5-4265-8aac-d5b3c3a1f691", "env": {}}, "results": [{"status": "success", "timing": [{"name": "compile", "started_at": "2023-07-07T13:05:47.222528Z", "completed_at": "2023-07-07T13:05:47.244173Z"}, {"name": "execute", "started_at": "2023-07-07T13:05:47.251381Z", "completed_at": "2023-07-07T13:05:47.251381Z"}], "thread_id": "Thread-1 (worker)", "execution_time": 0.03879976272583008, "adapter_response": {}, "message": null, "failures": null, "unique_id": "model.villo_cjaminon_team1.str_villo"}, {"status": "success", "timing": [{"name": "compile", "started_at": "2023-07-07T13:05:47.234179Z", "completed_at": "2023-07-07T13:05:47.248098Z"}, {"name": "execute", "started_at": "2023-07-07T13:05:47.257896Z", "completed_at": "2023-07-07T13:05:47.257896Z"}], "thread_id": "Thread-2 (worker)", "execution_time": 0.04334259033203125, "adapter_response": {}, "message": null, "failures": null, "unique_id": "model.villo_cjaminon_team1.str_weather"}, {"status": "success", "timing": [{"name": "compile", "started_at": "2023-07-07T13:05:47.286717Z", "completed_at": "2023-07-07T13:05:47.299425Z"}, {"name": "execute", "started_at": "2023-07-07T13:05:47.307247Z", "completed_at": "2023-07-07T13:05:47.307247Z"}], "thread_id": "Thread-1 (worker)", "execution_time": 0.04157543182373047, "adapter_response": {}, "message": null, "failures": null, "unique_id": "model.villo_cjaminon_team1.str_trips_per_stand_per_day"}, {"status": "success", "timing": [{"name": "compile", "started_at": "2023-07-07T13:05:47.281459Z", "completed_at": "2023-07-07T13:05:47.299929Z"}, {"name": "execute", "started_at": "2023-07-07T13:05:47.309392Z", "completed_at": "2023-07-07T13:05:47.309392Z"}], "thread_id": "Thread-3 (worker)", "execution_time": 0.046520233154296875, "adapter_response": {}, "message": null, "failures": null, "unique_id": "model.villo_cjaminon_team1.str_bikes_per_stand_per_hour"}, {"status": "success", "timing": [{"name": "compile", "started_at": "2023-07-07T13:05:47.276674Z", "completed_at": "2023-07-07T13:05:47.300943Z"}, {"name": "execute", "started_at": "2023-07-07T13:05:47.310394Z", "completed_at": "2023-07-07T13:05:47.310394Z"}], "thread_id": "Thread-4 (worker)", "execution_time": 0.04902029037475586, "adapter_response": {}, "message": null, "failures": null, "unique_id": "model.villo_cjaminon_team1.analytics_total_bikes"}, {"status": "success", "timing": [{"name": "compile", "started_at": "2023-07-07T13:05:47.292892Z", "completed_at": "2023-07-07T13:05:47.304186Z"}, {"name": "execute", "started_at": "2023-07-07T13:05:47.312392Z", "completed_at": "2023-07-07T13:05:47.312392Z"}], "thread_id": "Thread-2 (worker)", "execution_time": 0.04294991493225098, "adapter_response": {}, "message": null, "failures": null, "unique_id": "model.villo_cjaminon_team1.str_trips_per_stand_per_hour"}, {"status": "success", "timing": [{"name": "compile", "started_at": "2023-07-07T13:05:47.328394Z", "completed_at": "2023-07-07T13:05:47.369438Z"}, {"name": "execute", "started_at": "2023-07-07T13:05:47.373420Z", "completed_at": "2023-07-07T13:05:47.373923Z"}], "thread_id": "Thread-1 (worker)", "execution_time": 0.055639028549194336, "adapter_response": {}, "message": null, "failures": null, "unique_id": "model.villo_cjaminon_team1.str_villo_communes"}, {"status": "success", "timing": [{"name": "compile", "started_at": "2023-07-07T13:05:47.334339Z", "completed_at": "2023-07-07T13:05:47.374999Z"}, {"name": "execute", "started_at": "2023-07-07T13:05:47.383028Z", "completed_at": "2023-07-07T13:05:47.383028Z"}], "thread_id": "Thread-3 (worker)", "execution_time": 0.06363558769226074, "adapter_response": {}, "message": null, "failures": null, "unique_id": "test.villo_cjaminon_team1.lat_lon_validity"}, {"status": "success", "timing": [{"name": "compile", "started_at": "2023-07-07T13:05:47.340409Z", "completed_at": "2023-07-07T13:05:47.376041Z"}, {"name": "execute", "started_at": "2023-07-07T13:05:47.384033Z", "completed_at": "2023-07-07T13:05:47.384033Z"}], "thread_id": "Thread-4 (worker)", "execution_time": 0.06363630294799805, "adapter_response": {}, "message": null, "failures": null, "unique_id": "test.villo_cjaminon_team1.not_null_str_villo_address.aae9069ce2"}, {"status": "success", "timing": [{"name": "compile", "started_at": "2023-07-07T13:05:47.360734Z", "completed_at": "2023-07-07T13:05:47.378039Z"}, {"name": "execute", "started_at": "2023-07-07T13:05:47.386029Z", "completed_at": "2023-07-07T13:05:47.386029Z"}], "thread_id": "Thread-2 (worker)", "execution_time": 0.06363677978515625, "adapter_response": {}, "message": null, "failures": null, "unique_id": "test.villo_cjaminon_team1.not_null_str_villo_available_bike_stands.367e6e3bc8"}, {"status": "success", "timing": [{"name": "compile", "started_at": "2023-07-07T13:05:47.392028Z", "completed_at": "2023-07-07T13:05:47.402086Z"}, {"name": "execute", "started_at": "2023-07-07T13:05:47.423092Z", "completed_at": "2023-07-07T13:05:47.423092Z"}], "thread_id": "Thread-1 (worker)", "execution_time": 0.04006671905517578, "adapter_response": {}, "message": null, "failures": null, "unique_id": "test.villo_cjaminon_team1.not_null_str_villo_banking.7aa28b1e7c"}, {"status": "success", "timing": [{"name": "compile", "started_at": "2023-07-07T13:05:47.406092Z", "completed_at": "2023-07-07T13:05:47.426853Z"}, {"name": "execute", "started_at": "2023-07-07T13:05:47.434664Z", "completed_at": "2023-07-07T13:05:47.434664Z"}], "thread_id": "Thread-3 (worker)", "execution_time": 0.03964114189147949, "adapter_response": {}, "message": null, "failures": null, "unique_id": "test.villo_cjaminon_team1.not_null_str_villo_geopoint.333c37eaca"}, {"status": "success", "timing": [{"name": "compile", "started_at": "2023-07-07T13:05:47.418090Z", "completed_at": "2023-07-07T13:05:47.427355Z"}, {"name": "execute", "started_at": "2023-07-07T13:05:47.435672Z", "completed_at": "2023-07-07T13:05:47.435672Z"}], "thread_id": "Thread-2 (worker)", "execution_time": 0.039641380310058594, "adapter_response": {}, "message": null, "failures": null, "unique_id": "test.villo_cjaminon_team1.not_null_str_villo_last_update_ts.804bce5583"}, {"status": "success", "timing": [{"name": "compile", "started_at": "2023-07-07T13:05:47.412090Z", "completed_at": "2023-07-07T13:05:47.429424Z"}, {"name": "execute", "started_at": "2023-07-07T13:05:47.436669Z", "completed_at": "2023-07-07T13:05:47.436669Z"}], "thread_id": "Thread-4 (worker)", "execution_time": 0.04164266586303711, "adapter_response": {}, "message": null, "failures": null, "unique_id": "test.villo_cjaminon_team1.not_null_str_villo_last_update.9fb3d6994d"}, {"status": "success", "timing": [{"name": "compile", "started_at": "2023-07-07T13:05:47.441669Z", "completed_at": "2023-07-07T13:05:47.453671Z"}, {"name": "execute", "started_at": "2023-07-07T13:05:47.470670Z", "completed_at": "2023-07-07T13:05:47.470670Z"}], "thread_id": "Thread-1 (worker)", "execution_time": 0.038507699966430664, "adapter_response": {}, "message": null, "failures": null, "unique_id": "test.villo_cjaminon_team1.not_null_str_villo_lat.930a6087d1"}, {"status": "success", "timing": [{"name": "compile", "started_at": "2023-07-07T13:05:47.461669Z", "completed_at": "2023-07-07T13:05:47.474872Z"}, {"name": "execute", "started_at": "2023-07-07T13:05:47.482024Z", "completed_at": "2023-07-07T13:05:47.482024Z"}], "thread_id": "Thread-2 (worker)", "execution_time": 0.0413515567779541, "adapter_response": {}, "message": null, "failures": null, "unique_id": "test.villo_cjaminon_team1.not_null_str_villo_long.dd0500b32e"}, {"status": "success", "timing": [{"name": "compile", "started_at": "2023-07-07T13:05:47.456669Z", "completed_at": "2023-07-07T13:05:47.476025Z"}, {"name": "execute", "started_at": "2023-07-07T13:05:47.483023Z", "completed_at": "2023-07-07T13:05:47.483023Z"}], "thread_id": "Thread-3 (worker)", "execution_time": 0.0433504581451416, "adapter_response": {}, "message": null, "failures": null, "unique_id": "test.villo_cjaminon_team1.not_null_str_villo_load_timestamp.10a19ea2c3"}, {"status": "success", "timing": [{"name": "compile", "started_at": "2023-07-07T13:05:47.465670Z", "completed_at": "2023-07-07T13:05:47.477023Z"}, {"name": "execute", "started_at": "2023-07-07T13:05:47.483023Z", "completed_at": "2023-07-07T13:05:47.483023Z"}], "thread_id": "Thread-4 (worker)", "execution_time": 0.04235100746154785, "adapter_response": {}, "message": null, "failures": null, "unique_id": "test.villo_cjaminon_team1.not_null_str_villo_name.852d6b149a"}, {"status": "success", "timing": [{"name": "compile", "started_at": "2023-07-07T13:05:47.484023Z", "completed_at": "2023-07-07T13:05:47.497605Z"}, {"name": "execute", "started_at": "2023-07-07T13:05:47.504604Z", "completed_at": "2023-07-07T13:05:47.504604Z"}], "thread_id": "Thread-1 (worker)", "execution_time": 0.04058122634887695, "adapter_response": {}, "message": null, "failures": null, "unique_id": "test.villo_cjaminon_team1.not_null_str_villo_number.e2dfa66ff8"}, {"status": "success", "timing": [{"name": "compile", "started_at": "2023-07-07T13:05:47.505603Z", "completed_at": "2023-07-07T13:05:47.526703Z"}, {"name": "execute", "started_at": "2023-07-07T13:05:47.533210Z", "completed_at": "2023-07-07T13:05:47.533210Z"}], "thread_id": "Thread-2 (worker)", "execution_time": 0.0406041145324707, "adapter_response": {}, "message": null, "failures": null, "unique_id": "test.villo_cjaminon_team1.not_null_str_villo_status.53c58c33fb"}, {"status": "success", "timing": [{"name": "compile", "started_at": "2023-07-07T13:05:47.510604Z", "completed_at": "2023-07-07T13:05:47.527705Z"}, {"name": "execute", "started_at": "2023-07-07T13:05:47.534210Z", "completed_at": "2023-07-07T13:05:47.534210Z"}], "thread_id": "Thread-3 (worker)", "execution_time": 0.04200434684753418, "adapter_response": {}, "message": null, "failures": null, "unique_id": "test.villo_cjaminon_team1.unique_str_villo_contract_name.449d83feea"}, {"status": "success", "timing": [{"name": "compile", "started_at": "2023-07-07T13:05:47.519605Z", "completed_at": "2023-07-07T13:05:47.530217Z"}, {"name": "execute", "started_at": "2023-07-07T13:05:47.541211Z", "completed_at": "2023-07-07T13:05:47.541211Z"}], "thread_id": "Thread-4 (worker)", "execution_time": 0.04202461242675781, "adapter_response": {}, "message": null, "failures": null, "unique_id": "test.villo_cjaminon_team1.unique_str_villo_uid.6136971f98"}, {"status": "success", "timing": [{"name": "compile", "started_at": "2023-07-07T13:05:47.535210Z", "completed_at": "2023-07-07T13:05:47.547628Z"}, {"name": "execute", "started_at": "2023-07-07T13:05:47.553629Z", "completed_at": "2023-07-07T13:05:47.553629Z"}], "thread_id": "Thread-1 (worker)", "execution_time": 0.035422563552856445, "adapter_response": {}, "message": null, "failures": null, "unique_id": "model.villo_cjaminon_team1.str_weather_communes"}, {"status": "success", "timing": [{"name": "compile", "started_at": "2023-07-07T13:05:47.554628Z", "completed_at": "2023-07-07T13:05:47.570628Z"}, {"name": "execute", "started_at": "2023-07-07T13:05:47.577640Z", "completed_at": "2023-07-07T13:05:47.577640Z"}], "thread_id": "Thread-2 (worker)", "execution_time": 0.03299880027770996, "adapter_response": {}, "message": null, "failures": null, "unique_id": "model.villo_cjaminon_team1.str_weather_per_day"}, {"status": "success", "timing": [{"name": "compile", "started_at": "2023-07-07T13:05:47.558631Z", "completed_at": "2023-07-07T13:05:47.574630Z"}, {"name": "execute", "started_at": "2023-07-07T13:05:47.582629Z", "completed_at": "2023-07-07T13:05:47.582629Z"}], "thread_id": "Thread-3 (worker)", "execution_time": 0.04000091552734375, "adapter_response": {}, "message": null, "failures": null, "unique_id": "test.villo_cjaminon_team1.not_null_str_weather_apparent_temperature.62246cf5e6"}, {"status": "success", "timing": [{"name": "compile", "started_at": "2023-07-07T13:05:47.564628Z", "completed_at": "2023-07-07T13:05:47.576634Z"}, {"name": "execute", "started_at": "2023-07-07T13:05:47.587629Z", "completed_at": "2023-07-07T13:05:47.587629Z"}], "thread_id": "Thread-4 (worker)", "execution_time": 0.04000258445739746, "adapter_response": {}, "message": null, "failures": null, "unique_id": "test.villo_cjaminon_team1.not_null_str_weather_cloud_cover.4fac46115d"}, {"status": "success", "timing": [{"name": "compile", "started_at": "2023-07-07T13:05:47.582629Z", "completed_at": "2023-07-07T13:05:47.593630Z"}, {"name": "execute", "started_at": "2023-07-07T13:05:47.604824Z", "completed_at": "2023-07-07T13:05:47.604824Z"}], "thread_id": "Thread-1 (worker)", "execution_time": 0.03312563896179199, "adapter_response": {}, "message": null, "failures": null, "unique_id": "test.villo_cjaminon_team1.not_null_str_weather_dew_point.2cb5fddb72"}, {"status": "success", "timing": [{"name": "compile", "started_at": "2023-07-07T13:05:47.599635Z", "completed_at": "2023-07-07T13:05:47.614753Z"}, {"name": "execute", "started_at": "2023-07-07T13:05:47.627254Z", "completed_at": "2023-07-07T13:05:47.627254Z"}], "thread_id": "Thread-2 (worker)", "execution_time": 0.03862285614013672, "adapter_response": {}, "message": null, "failures": null, "unique_id": "test.villo_cjaminon_team1.not_null_str_weather_geopoint.5d58c3a0f7"}, {"status": "success", "timing": [{"name": "compile", "started_at": "2023-07-07T13:05:47.609752Z", "completed_at": "2023-07-07T13:05:47.624044Z"}, {"name": "execute", "started_at": "2023-07-07T13:05:47.632254Z", "completed_at": "2023-07-07T13:05:47.632254Z"}], "thread_id": "Thread-3 (worker)", "execution_time": 0.04416370391845703, "adapter_response": {}, "message": null, "failures": null, "unique_id": "test.villo_cjaminon_team1.not_null_str_weather_humidity.f03e57ac35"}, {"status": "success", "timing": [{"name": "compile", "started_at": "2023-07-07T13:05:47.615750Z", "completed_at": "2023-07-07T13:05:47.629253Z"}, {"name": "execute", "started_at": "2023-07-07T13:05:47.642796Z", "completed_at": "2023-07-07T13:05:47.642796Z"}], "thread_id": "Thread-4 (worker)", "execution_time": 0.04816746711730957, "adapter_response": {}, "message": null, "failures": null, "unique_id": "test.villo_cjaminon_team1.not_null_str_weather_icon.c584ae0d2f"}, {"status": "success", "timing": [{"name": "compile", "started_at": "2023-07-07T13:05:47.634253Z", "completed_at": "2023-07-07T13:05:47.647800Z"}, {"name": "execute", "started_at": "2023-07-07T13:05:47.659108Z", "completed_at": "2023-07-07T13:05:47.659108Z"}], "thread_id": "Thread-1 (worker)", "execution_time": 0.04284381866455078, "adapter_response": {}, "message": null, "failures": null, "unique_id": "test.villo_cjaminon_team1.not_null_str_weather_latitude.96a8667b6f"}, {"status": "success", "timing": [{"name": "compile", "started_at": "2023-07-07T13:05:47.652106Z", "completed_at": "2023-07-07T13:05:47.668102Z"}, {"name": "execute", "started_at": "2023-07-07T13:05:47.678103Z", "completed_at": "2023-07-07T13:05:47.678103Z"}], "thread_id": "Thread-2 (worker)", "execution_time": 0.04064059257507324, "adapter_response": {}, "message": null, "failures": null, "unique_id": "test.villo_cjaminon_team1.not_null_str_weather_longitude.81950f9483"}, {"status": "success", "timing": [{"name": "compile", "started_at": "2023-07-07T13:05:47.660107Z", "completed_at": "2023-07-07T13:05:47.676101Z"}, {"name": "execute", "started_at": "2023-07-07T13:05:47.685900Z", "completed_at": "2023-07-07T13:05:47.685900Z"}], "thread_id": "Thread-3 (worker)", "execution_time": 0.038025856018066406, "adapter_response": {}, "message": null, "failures": null, "unique_id": "test.villo_cjaminon_team1.not_null_str_weather_pressure.93988c5f57"}, {"status": "success", "timing": [{"name": "compile", "started_at": "2023-07-07T13:05:47.670106Z", "completed_at": "2023-07-07T13:05:47.682678Z"}, {"name": "execute", "started_at": "2023-07-07T13:05:47.694005Z", "completed_at": "2023-07-07T13:05:47.694005Z"}], "thread_id": "Thread-4 (worker)", "execution_time": 0.0397946834564209, "adapter_response": {}, "message": null, "failures": null, "unique_id": "test.villo_cjaminon_team1.not_null_str_weather_recording_time_ts.b247b28775"}, {"status": "success", "timing": [{"name": "compile", "started_at": "2023-07-07T13:05:47.688901Z", "completed_at": "2023-07-07T13:05:47.699895Z"}, {"name": "execute", "started_at": "2023-07-07T13:05:47.708897Z", "completed_at": "2023-07-07T13:05:47.708897Z"}], "thread_id": "Thread-1 (worker)", "execution_time": 0.036852359771728516, "adapter_response": {}, "message": null, "failures": null, "unique_id": "test.villo_cjaminon_team1.not_null_str_weather_summary.a16491cc8c"}, {"status": "success", "timing": [{"name": "compile", "started_at": "2023-07-07T13:05:47.701895Z", "completed_at": "2023-07-07T13:05:47.715129Z"}, {"name": "execute", "started_at": "2023-07-07T13:05:47.730958Z", "completed_at": "2023-07-07T13:05:47.730958Z"}], "thread_id": "Thread-2 (worker)", "execution_time": 0.04149436950683594, "adapter_response": {}, "message": null, "failures": null, "unique_id": "test.villo_cjaminon_team1.too_hot"}, {"status": "success", "timing": [{"name": "compile", "started_at": "2023-07-07T13:05:47.709896Z", "completed_at": "2023-07-07T13:05:47.729584Z"}, {"name": "execute", "started_at": "2023-07-07T13:05:47.738789Z", "completed_at": "2023-07-07T13:05:47.738789Z"}], "thread_id": "Thread-3 (worker)", "execution_time": 0.045163631439208984, "adapter_response": {}, "message": null, "failures": null, "unique_id": "model.villo_cjaminon_team1.analytics_avg_nbr_of_bikes_in_use_per_hour_with_weather"}, {"status": "success", "timing": [{"name": "compile", "started_at": "2023-07-07T13:05:47.721113Z", "completed_at": "2023-07-07T13:05:47.733969Z"}, {"name": "execute", "started_at": "2023-07-07T13:05:47.747073Z", "completed_at": "2023-07-07T13:05:47.747073Z"}], "thread_id": "Thread-4 (worker)", "execution_time": 0.04317736625671387, "adapter_response": {}, "message": null, "failures": null, "unique_id": "model.villo_cjaminon_team1.analytics_trips_weather_per_hour_from_delta"}, {"status": "success", "timing": [{"name": "compile", "started_at": "2023-07-07T13:05:47.741072Z", "completed_at": "2023-07-07T13:05:47.753080Z"}, {"name": "execute", "started_at": "2023-07-07T13:05:47.762369Z", "completed_at": "2023-07-07T13:05:47.762369Z"}], "thread_id": "Thread-1 (worker)", "execution_time": 0.039629459381103516, "adapter_response": {}, "message": null, "failures": null, "unique_id": "model.villo_cjaminon_team1.analytics_last_updates"}, {"status": "success", "timing": [{"name": "compile", "started_at": "2023-07-07T13:05:47.755071Z", "completed_at": "2023-07-07T13:05:47.769843Z"}, {"name": "execute", "started_at": "2023-07-07T13:05:47.783657Z", "completed_at": "2023-07-07T13:05:47.783657Z"}], "thread_id": "Thread-2 (worker)", "execution_time": 0.03976893424987793, "adapter_response": {}, "message": null, "failures": null, "unique_id": "model.villo_cjaminon_team1.analytics_stand_per_hour"}, {"status": "success", "timing": [{"name": "compile", "started_at": "2023-07-07T13:05:47.763514Z", "completed_at": "2023-07-07T13:05:47.781655Z"}, {"name": "execute", "started_at": "2023-07-07T13:05:47.788890Z", "completed_at": "2023-07-07T13:05:47.788890Z"}], "thread_id": "Thread-3 (worker)", "execution_time": 0.038848161697387695, "adapter_response": {}, "message": null, "failures": null, "unique_id": "model.villo_cjaminon_team1.analytics_station_avg_hour"}, {"status": "success", "timing": [{"name": "compile", "started_at": "2023-07-07T13:05:47.772850Z", "completed_at": "2023-07-07T13:05:47.786851Z"}, {"name": "execute", "started_at": "2023-07-07T13:05:47.799019Z", "completed_at": "2023-07-07T13:05:47.799019Z"}], "thread_id": "Thread-4 (worker)", "execution_time": 0.042075157165527344, "adapter_response": {}, "message": null, "failures": null, "unique_id": "model.villo_cjaminon_team1.str_villo_communes_weather"}, {"status": "success", "timing": [{"name": "compile", "started_at": "2023-07-07T13:05:47.793918Z", "completed_at": "2023-07-07T13:05:47.804921Z"}, {"name": "execute", "started_at": "2023-07-07T13:05:47.820875Z", "completed_at": "2023-07-07T13:05:47.820875Z"}], "thread_id": "Thread-1 (worker)", "execution_time": 0.04667854309082031, "adapter_response": {}, "message": null, "failures": null, "unique_id": "test.villo_cjaminon_team1.unique_str_villo_communes_uid.9a3a60eb9d"}, {"status": "success", "timing": [{"name": "compile", "started_at": "2023-07-07T13:05:47.808190Z", "completed_at": "2023-07-07T13:05:47.831006Z"}, {"name": "execute", "started_at": "2023-07-07T13:05:47.845772Z", "completed_at": "2023-07-07T13:05:47.845772Z"}], "thread_id": "Thread-2 (worker)", "execution_time": 0.05084991455078125, "adapter_response": {}, "message": null, "failures": null, "unique_id": "model.villo_cjaminon_team1.analytics_stand_weather"}, {"status": "success", "timing": [{"name": "compile", "started_at": "2023-07-07T13:05:47.822241Z", "completed_at": "2023-07-07T13:05:47.844263Z"}, {"name": "execute", "started_at": "2023-07-07T13:05:47.852770Z", "completed_at": "2023-07-07T13:05:47.852770Z"}], "thread_id": "Thread-3 (worker)", "execution_time": 0.058573246002197266, "adapter_response": {}, "message": null, "failures": null, "unique_id": "model.villo_cjaminon_team1.analytics_trips_weather_communes_per_stand_per_day"}, {"status": "success", "timing": [{"name": "compile", "started_at": "2023-07-07T13:05:47.834773Z", "completed_at": "2023-07-07T13:05:47.848774Z"}, {"name": "execute", "started_at": "2023-07-07T13:05:47.865493Z", "completed_at": "2023-07-07T13:05:47.865493Z"}], "thread_id": "Thread-4 (worker)", "execution_time": 0.05080986022949219, "adapter_response": {}, "message": null, "failures": null, "unique_id": "model.villo_cjaminon_team1.analytics_trips_weather_communes_per_stand_per_hour"}, {"status": "success", "timing": [{"name": "compile", "started_at": "2023-07-07T13:05:47.855991Z", "completed_at": "2023-07-07T13:05:47.872160Z"}, {"name": "execute", "started_at": "2023-07-07T13:05:47.885596Z", "completed_at": "2023-07-07T13:05:47.885596Z"}], "thread_id": "Thread-1 (worker)", "execution_time": 0.04250812530517578, "adapter_response": {}, "message": null, "failures": null, "unique_id": "test.villo_cjaminon_team1.unique_str_weather_communes_recording_time_ts.fd3d968d01"}, {"status": "success", "timing": [{"name": "compile", "started_at": "2023-07-07T13:05:47.873702Z", "completed_at": "2023-07-07T13:05:47.891169Z"}, {"name": "execute", "started_at": "2023-07-07T13:05:47.893705Z", "completed_at": "2023-07-07T13:05:47.893705Z"}], "thread_id": "Thread-2 (worker)", "execution_time": 0.02872467041015625, "adapter_response": {}, "message": null, "failures": null, "unique_id": "model.villo_cjaminon_team1.analytics_avg_nbr_of_bikes_in_use_per_day_with_weather"}], "elapsed_time": 2.6597790718078613, "args": {"log_level_file": "debug", "macro_debugging": false, "static_parser": true, "log_format": "default", "vars": {}, "write_json": true, "send_anonymous_usage_stats": true, "introspect": true, "quiet": false, "log_level": "info", "warn_error_options": {"include": [], "exclude": []}, "print": true, "strict_mode": false, "partial_parse": true, "profiles_dir": "C:\\Users\\cjaminonderoeck\\.dbt", "exclude": [], "populate_cache": true, "project_dir": "C:\\Users\\cjaminonderoeck\\OneDrive - Business & Decision Europe\\Documents\\OpenMetadata\\villo-e2e-01\\dbt", "favor_state": false, "which": "generate", "enable_legacy_logger": false, "printer_width": 80, "log_path": "C:\\Users\\cjaminonderoeck\\OneDrive - Business & Decision Europe\\Documents\\OpenMetadata\\villo-e2e-01\\dbt\\logs", "indirect_selection": "eager", "use_colors_file": true, "select": [], "compile": true, "version_check": true, "cache_selected_only": false, "use_colors": true, "log_format_file": "debug", "defer": false}}
